{"2": {"0": {"[1.0, 0]": {"num_count": 1879, "sum_payoffs": 488.30510517362404, "action": [1.0, 0]}, "[0.0, 0]": {"num_count": 721, "sum_payoffs": 146.72099997310045, "action": [0.0, 0]}}, "1": {"[0.0, 0]": {"num_count": 730, "sum_payoffs": 149.51549997258826, "action": [0.0, 0]}, "[1.0, 0]": {"num_count": 1870, "sum_payoffs": 485.9966051740469, "action": [1.0, 0]}}}, "1": {"0": {"[1.0, 0]": {"num_count": 1308, "sum_payoffs": 354.02999993510434, "action": [1.0, 0]}, "[0.0, 0]": {"num_count": 1292, "sum_payoffs": 348.8699999360498, "action": [0.0, 0]}}, "1": {"[1.0, 0]": {"num_count": 1308, "sum_payoffs": 354.02999993510434, "action": [1.0, 0]}, "[0.0, 0]": {"num_count": 1292, "sum_payoffs": 348.8699999360498, "action": [0.0, 0]}}}}