{"2": {"0": {"[1.0, 0]": {"num_count": 2323, "sum_payoffs": 881.3609994711641, "action": [1.0, 0]}, "[0.0, 0]": {"num_count": 777, "sum_payoffs": 247.67774985138996, "action": [0.0, 0]}}, "1": {"[1.0, 0]": {"num_count": 2309, "sum_payoffs": 877.3514994735708, "action": [1.0, 0]}, "[0.0, 0]": {"num_count": 791, "sum_payoffs": 253.8742498476718, "action": [0.0, 0]}}}, "1": {"0": {"[0.0, 0]": {"num_count": 1093, "sum_payoffs": 419.98499974801666, "action": [0.0, 0]}, "[1.0, 0]": {"num_count": 2007, "sum_payoffs": 835.1099994989631, "action": [1.0, 0]}}, "1": {"[1.0, 0]": {"num_count": 1995, "sum_payoffs": 830.2499995018788, "action": [1.0, 0]}, "[0.0, 0]": {"num_count": 1105, "sum_payoffs": 425.65499974461494, "action": [0.0, 0]}}}}