{"2": {"0": {"[1.0, 0]": {"num_count": 56, "sum_payoffs": 14.848282892014675, "action": [1.0, 0]}, "[0.0, 0]": {"num_count": 44, "sum_payoffs": 9.076499998335976, "action": [0.0, 0]}}, "1": {"[1.0, 0]": {"num_count": 53, "sum_payoffs": 13.760407892214113, "action": [1.0, 0]}, "[0.0, 0]": {"num_count": 47, "sum_payoffs": 10.893374998002889, "action": [0.0, 0]}}}, "1": {"0": {"[1.0, 0]": {"num_count": 55, "sum_payoffs": 12.847499997644613, "action": [1.0, 0]}, "[0.0, 0]": {"num_count": 45, "sum_payoffs": 8.75249999839537, "action": [0.0, 0]}}, "1": {"[0.0, 0]": {"num_count": 46, "sum_payoffs": 9.056249998339682, "action": [0.0, 0]}, "[1.0, 0]": {"num_count": 54, "sum_payoffs": 12.543749997700301, "action": [1.0, 0]}}}}