{"2": {"0": {"[0.0, 0]": {"num_count": 204, "sum_payoffs": 43.91410854275088, "action": [0.0, 0]}, "[1.0, 0]": {"num_count": 1896, "sum_payoffs": 528.2161873811414, "action": [1.0, 0]}}, "1": {"[1.0, 0]": {"num_count": 1972, "sum_payoffs": 553.9609834279798, "action": [1.0, 0]}, "[0.0, 0]": {"num_count": 128, "sum_payoffs": 26.643937494005076, "action": [0.0, 0]}}}, "1": {"0": {"[1.0, 0]": {"num_count": 1872, "sum_payoffs": 575.7524998704633, "action": [1.0, 0]}, "[0.0, 0]": {"num_count": 228, "sum_payoffs": 60.36749998641708, "action": [0.0, 0]}}, "1": {"[1.0, 0]": {"num_count": 1953, "sum_payoffs": 603.2418748642833, "action": [1.0, 0]}, "[0.0, 0]": {"num_count": 147, "sum_payoffs": 37.738124991508876, "action": [0.0, 0]}}}}