{"2": {"0": {"[0.0, 0]": {"num_count": 661, "sum_payoffs": 208.85849992690035, "action": [0.0, 0]}, "[1.0, 0]": {"num_count": 1939, "sum_payoffs": 737.2012497419912, "action": [1.0, 0]}}, "1": {"[1.0, 0]": {"num_count": 1923, "sum_payoffs": 733.7384997432023, "action": [1.0, 0]}, "[0.0, 0]": {"num_count": 677, "sum_payoffs": 216.33074992428524, "action": [0.0, 0]}}}, "1": {"0": {"[0.0, 0]": {"num_count": 914, "sum_payoffs": 349.51499987767465, "action": [0.0, 0]}, "[1.0, 0]": {"num_count": 1686, "sum_payoffs": 703.0799997539114, "action": [1.0, 0]}}, "1": {"[1.0, 0]": {"num_count": 1684, "sum_payoffs": 702.6749997540531, "action": [1.0, 0]}, "[0.0, 0]": {"num_count": 916, "sum_payoffs": 350.7299998772494, "action": [0.0, 0]}}}}