{"2": {"0": {"[0.0, 0]": {"num_count": 731, "sum_payoffs": 131.5637999736873, "action": [0.0, 0]}, "[1.0, 0]": {"num_count": 1869, "sum_payoffs": 439.2706499121357, "action": [1.0, 0]}}, "1": {"[0.0, 0]": {"num_count": 743, "sum_payoffs": 135.61379997287776, "action": [0.0, 0]}, "[1.0, 0]": {"num_count": 1857, "sum_payoffs": 438.28244991233396, "action": [1.0, 0]}}}, "1": {"0": {"[0.0, 0]": {"num_count": 989, "sum_payoffs": 223.79849995523665, "action": [0.0, 0]}, "[1.0, 0]": {"num_count": 1611, "sum_payoffs": 408.59549991827276, "action": [1.0, 0]}}, "1": {"[1.0, 0]": {"num_count": 1607, "sum_payoffs": 407.8664999184186, "action": [1.0, 0]}, "[0.0, 0]": {"num_count": 993, "sum_payoffs": 225.256499954945, "action": [0.0, 0]}}}}