{"2": {"0": {"[0.0, 0]": {"num_count": 177, "sum_payoffs": 17.342437496097926, "action": [0.0, 0]}, "[1.0, 0]": {"num_count": 923, "sum_payoffs": 95.40023682064128, "action": [1.0, 0]}}, "1": {"[0.0, 0]": {"num_count": 183, "sum_payoffs": 16.34006249632346, "action": [0.0, 0]}, "[1.0, 0]": {"num_count": 917, "sum_payoffs": 90.75286182168685, "action": [1.0, 0]}}}, "1": {"0": {"[0.0, 0]": {"num_count": 230, "sum_payoffs": 20.06437499548559, "action": [0.0, 0]}, "[1.0, 0]": {"num_count": 870, "sum_payoffs": 92.32312497922639, "action": [1.0, 0]}}, "1": {"[1.0, 0]": {"num_count": 882, "sum_payoffs": 94.24687497879337, "action": [1.0, 0]}, "[0.0, 0]": {"num_count": 218, "sum_payoffs": 20.165624995462807, "action": [0.0, 0]}}}}