{"alphat_eff_gamelength_2": {"mean": 1.0, "variance": 0.0}, "runtime_gamelength_2": {"mean": 0.2574826717376709, "variance": 0.00031732746250781927}, "max_timestep": {"mean": 1.0, "variance": 0.0}, "alphat_eff_gamelength_1": {"mean": 1.0, "variance": 0.0}, "runtime_gamelength_1": {"mean": 0.16584901809692382, "variance": 9.447740436371529e-05}, "winner": {"mean": [0.1, 0.0], "variance": [0.09000000000000001, 0.0]}, "runtime": {"mean": 0.4235384464263916, "variance": 0.000580056788624006}, "T_terminal": {"mean": 2.0, "variance": 0.0}, "trajectory_0": {"mean": [[1.0, 0.0, 1.5707963267948966, 0.0], [1.0, 1.0, 1.5707963267948966, 1.0], [1.0, 2.0, 1.5707963267948966, 2.0]], "variance": [[0.0, 0.0, 0.0, 0.0], [0.0, 0.0, 0.0, 0.0], [0.0, 0.0, 0.0, 0.0]]}, "trajectory_1": {"mean": [[0.0, 1.0, 0.0, 0.0], [1.0, 1.0, 0.0, 1.0], [1.9, 1.0, 0.0, 2.0]], "variance": [[0.0, 0.0, 0.0, 0.0], [0.0, 0.0, 0.0, 0.0], [0.09, 0.0, 0.0, 0.0]]}, "coll_payoff_0": {"mean": [0.0, 0.0], "variance": [0.0, 0.0]}, "coll_payoff_1": {"mean": [0.0, 0.0], "variance": [0.0, 0.0]}, "payoff_total": {"mean": [[0.0, 0.0], [0.39374999991140625, 0.35624999991984374]], "variance": [[0.0, 0.0], [0.0031640624985761734, 0.003164062498576173]]}, "final_lead_payoff_0": {"mean": [0.525], "variance": [0.005625]}, "final_lead_payoff_1": {"mean": [0.475], "variance": [0.005625]}}