{"2": {"0": {"[1.0, 0]": {"num_count": 2255, "sum_payoffs": 231.3671742900386, "action": [1.0, 0]}, "[0.0, 0]": {"num_count": 1345, "sum_payoffs": 104.22337497655057, "action": [0.0, 0]}}, "1": {"[0.0, 0]": {"num_count": 1343, "sum_payoffs": 104.01918747659589, "action": [0.0, 0]}, "[1.0, 0]": {"num_count": 2257, "sum_payoffs": 231.75361178995075, "action": [1.0, 0]}}}, "1": {"0": {"[0.0, 0]": {"num_count": 1499, "sum_payoffs": 138.37499996886456, "action": [0.0, 0]}, "[1.0, 0]": {"num_count": 2101, "sum_payoffs": 228.04874994869343, "action": [1.0, 0]}}, "1": {"[1.0, 0]": {"num_count": 2098, "sum_payoffs": 227.74499994876174, "action": [1.0, 0]}, "[0.0, 0]": {"num_count": 1502, "sum_payoffs": 138.88124996875067, "action": [0.0, 0]}}}}