{"2": {"0": {"[1.0, 0]": {"num_count": 572, "sum_payoffs": 0.0, "action": [1.0, 0]}, "[0.0, 0]": {"num_count": 528, "sum_payoffs": 0.0, "action": [0.0, 0]}}, "1": {"[1.0, 0]": {"num_count": 532, "sum_payoffs": 0.0, "action": [1.0, 0]}, "[0.0, 0]": {"num_count": 568, "sum_payoffs": 0.0, "action": [0.0, 0]}}}, "1": {"0": {"[1.0, 0]": {"num_count": 547, "sum_payoffs": 0.0, "action": [1.0, 0]}, "[0.0, 0]": {"num_count": 553, "sum_payoffs": 0.0, "action": [0.0, 0]}}, "1": {"[1.0, 0]": {"num_count": 543, "sum_payoffs": 0.0, "action": [1.0, 0]}, "[0.0, 0]": {"num_count": 557, "sum_payoffs": 0.0, "action": [0.0, 0]}}}}