{"2": {"0": {"[1.0, 0]": {"num_count": 1065, "sum_payoffs": 213.37478285561713, "action": [1.0, 0]}, "[0.0, 0]": {"num_count": 535, "sum_payoffs": 81.17212498511815, "action": [0.0, 0]}}, "1": {"[0.0, 0]": {"num_count": 528, "sum_payoffs": 80.12924998530934, "action": [0.0, 0]}, "[1.0, 0]": {"num_count": 1072, "sum_payoffs": 216.2401578550918, "action": [1.0, 0]}}}, "1": {"0": {"[0.0, 0]": {"num_count": 624, "sum_payoffs": 115.1662499788874, "action": [0.0, 0]}, "[1.0, 0]": {"num_count": 976, "sum_payoffs": 210.08249996148373, "action": [1.0, 0]}}, "1": {"[0.0, 0]": {"num_count": 628, "sum_payoffs": 116.1787499787018, "action": [0.0, 0]}, "[1.0, 0]": {"num_count": 972, "sum_payoffs": 209.27249996163226, "action": [1.0, 0]}}}}