{"2": {"0": {"[0.0, 0]": {"num_count": 50, "sum_payoffs": 8.537249998434836, "action": [0.0, 0]}, "[1.0, 0]": {"num_count": 50, "sum_payoffs": 8.63996052473179, "action": [1.0, 0]}}, "1": {"[0.0, 0]": {"num_count": 50, "sum_payoffs": 8.354999998468248, "action": [0.0, 0]}, "[1.0, 0]": {"num_count": 50, "sum_payoffs": 8.579210524742926, "action": [1.0, 0]}}}, "1": {"0": {"[0.0, 0]": {"num_count": 47, "sum_payoffs": 6.059999998888994, "action": [0.0, 0]}, "[1.0, 0]": {"num_count": 53, "sum_payoffs": 8.437499998453118, "action": [1.0, 0]}}, "1": {"[1.0, 0]": {"num_count": 56, "sum_payoffs": 9.847499998194618, "action": [1.0, 0]}, "[0.0, 0]": {"num_count": 44, "sum_payoffs": 5.3249999990237455, "action": [0.0, 0]}}}}