{"2": {"0": {"[0.0, 0]": {"num_count": 933, "sum_payoffs": 302.53499989411347, "action": [0.0, 0]}, "[1.0, 0]": {"num_count": 2667, "sum_payoffs": 1009.1182496468438, "action": [1.0, 0]}}, "1": {"[1.0, 0]": {"num_count": 2652, "sum_payoffs": 1004.5619996484381, "action": [1.0, 0]}, "[0.0, 0]": {"num_count": 948, "sum_payoffs": 308.9137498918806, "action": [0.0, 0]}}}, "1": {"0": {"[1.0, 0]": {"num_count": 2350, "sum_payoffs": 976.6574996581303, "action": [1.0, 0]}, "[0.0, 0]": {"num_count": 1250, "sum_payoffs": 480.7349998317518, "action": [0.0, 0]}}, "1": {"[0.0, 0]": {"num_count": 1248, "sum_payoffs": 480.12749983196437, "action": [0.0, 0]}, "[1.0, 0]": {"num_count": 2352, "sum_payoffs": 978.0749996576341, "action": [1.0, 0]}}}}