{"alphat_eff_gamelength_5": {"mean": 0.7692307692307693, "variance": 0.0}, "runtime_gamelength_5": {"mean": 18.24714825153351, "variance": 0.46629182321609564}, "max_timestep": {"mean": 5.0, "variance": 0.0}, "winner": {"mean": [0.0, 0.0], "variance": [0.0, 0.0]}, "runtime": {"mean": 18.247418546676634, "variance": 0.46629902384638855}, "T_terminal": {"mean": 1.0, "variance": 0.0}, "trajectory_0": {"mean": [[1.0, 3.0, 0.0, 0.0], [2.9, 3.0, -0.47123889803846897, 1.0]], "variance": [[0.0, 0.0, 0.0, 0.0], [0.09, 0.0, 1.5051146711661272, 0.0]]}, "trajectory_1": {"mean": [[3.0, 3.0, 0.0, 0.0], [4.0, 3.0, 0.0, 1.0]], "variance": [[0.0, 0.0, 0.0, 0.0], [0.0, 0.0, 0.4934802200544679, 0.0]]}, "coll_payoff_0": {"mean": [1.0], "variance": [0.0]}, "lead_payoff_0": {"mean": [0.6333333333333334], "variance": [0.01]}, "coll_payoff_1": {"mean": [1.0], "variance": [0.0]}, "lead_payoff_1": {"mean": [0.3666666666666667], "variance": [0.009999999999999998]}, "payoff_total": {"mean": [[0.5802681991506162, 0.586398467346606]], "variance": [[0.0005552252607869494, 0.0005552252607869478]]}, "final_lead_payoff_0": {"mean": [0.46206896551724136], "variance": [0.00010701545778834726]}, "final_lead_payoff_1": {"mean": [0.5379310344827586], "variance": [0.00010701545778834761]}}