{"2": {"0": {"[0.0, 0]": {"num_count": 222, "sum_payoffs": 47.667937489274735, "action": [0.0, 0]}, "[1.0, 0]": {"num_count": 2878, "sum_payoffs": 802.5353287667822, "action": [1.0, 0]}}, "1": {"[1.0, 0]": {"num_count": 2919, "sum_payoffs": 816.6850162635981, "action": [1.0, 0]}, "[0.0, 0]": {"num_count": 181, "sum_payoffs": 33.51824999245835, "action": [0.0, 0]}}}, "1": {"0": {"[0.0, 0]": {"num_count": 223, "sum_payoffs": 60.67124998634878, "action": [0.0, 0]}, "[1.0, 0]": {"num_count": 2877, "sum_payoffs": 898.0312497980055, "action": [1.0, 0]}}, "1": {"[1.0, 0]": {"num_count": 229, "sum_payoffs": 73.34999998349596, "action": [1.0, 0]}, "[0.0, 0]": {"num_count": 2871, "sum_payoffs": 852.5474998082319, "action": [0.0, 0]}}}}