{"2": {"0": {"[1.0, 0]": {"num_count": 56, "sum_payoffs": 9.955361839865306, "action": [1.0, 0]}, "[0.0, 0]": {"num_count": 44, "sum_payoffs": 6.445450656444516, "action": [0.0, 0]}}, "1": {"[1.0, 0]": {"num_count": 46, "sum_payoffs": 8.90662499799601, "action": [1.0, 0]}, "[0.0, 0]": {"num_count": 54, "sum_payoffs": 7.767562498252303, "action": [0.0, 0]}}}, "1": {"0": {"[0.0, 0]": {"num_count": 51, "sum_payoffs": 7.509374998310388, "action": [0.0, 0]}, "[1.0, 0]": {"num_count": 49, "sum_payoffs": 8.943749997987652, "action": [1.0, 0]}}, "1": {"[1.0, 0]": {"num_count": 47, "sum_payoffs": 4.674374998948265, "action": [1.0, 0]}, "[0.0, 0]": {"num_count": 53, "sum_payoffs": 3.172499999286187, "action": [0.0, 0]}}}}