{"2": {"0": {"[0.0, 0]": {"num_count": 190, "sum_payoffs": 38.27981249138703, "action": [0.0, 0]}, "[1.0, 0]": {"num_count": 3410, "sum_payoffs": 945.9205162345172, "action": [1.0, 0]}}, "1": {"[0.0, 0]": {"num_count": 252, "sum_payoffs": 54.474749987743195, "action": [0.0, 0]}, "[1.0, 0]": {"num_count": 3348, "sum_payoffs": 934.9197037369926, "action": [1.0, 0]}}}, "1": {"0": {"[1.0, 0]": {"num_count": 3415, "sum_payoffs": 1045.957499764743, "action": [1.0, 0]}, "[0.0, 0]": {"num_count": 185, "sum_payoffs": 49.58437498884337, "action": [0.0, 0]}}, "1": {"[1.0, 0]": {"num_count": 3370, "sum_payoffs": 1031.0737497680946, "action": [1.0, 0]}, "[0.0, 0]": {"num_count": 230, "sum_payoffs": 62.038124986041204, "action": [0.0, 0]}}}}