{"2": {"0": {"[0.0, 0]": {"num_count": 258, "sum_payoffs": 34.41374999369072, "action": [0.0, 0]}, "[1.0, 0]": {"num_count": 3342, "sum_payoffs": 622.2526577806893, "action": [1.0, 0]}}, "1": {"[0.0, 0]": {"num_count": 234, "sum_payoffs": 31.28062499426515, "action": [0.0, 0]}, "[1.0, 0]": {"num_count": 3366, "sum_payoffs": 633.5870327786129, "action": [1.0, 0]}}}, "1": {"0": {"[1.0, 0]": {"num_count": 3330, "sum_payoffs": 682.312499874939, "action": [1.0, 0]}, "[0.0, 0]": {"num_count": 270, "sum_payoffs": 46.21499999152725, "action": [0.0, 0]}}, "1": {"[0.0, 0]": {"num_count": 248, "sum_payoffs": 43.9874999919356, "action": [0.0, 0]}, "[1.0, 0]": {"num_count": 3352, "sum_payoffs": 688.1849998738637, "action": [1.0, 0]}}}}