{"2": {"0": {"[1.0, 0]": {"num_count": 1063, "sum_payoffs": 6.186315787824, "action": [1.0, 0]}, "[0.0, 0]": {"num_count": 1037, "sum_payoffs": 5.42368420908, "action": [0.0, 0]}}, "1": {"[1.0, 0]": {"num_count": 1040, "sum_payoffs": 5.759999998464, "action": [1.0, 0]}, "[0.0, 0]": {"num_count": 1060, "sum_payoffs": 5.84999999844, "action": [0.0, 0]}}}, "1": {"0": {"[0.0, 0]": {"num_count": 989, "sum_payoffs": 0.0, "action": [0.0, 0]}, "[1.0, 0]": {"num_count": 1111, "sum_payoffs": 1.79999999952, "action": [1.0, 0]}}, "1": {"[0.0, 0]": {"num_count": 1024, "sum_payoffs": 0.89999999976, "action": [0.0, 0]}, "[1.0, 0]": {"num_count": 1076, "sum_payoffs": 0.89999999976, "action": [1.0, 0]}}}}