{"2": {"0": {"[0.0, 0]": {"num_count": 247, "sum_payoffs": 32.54062499267831, "action": [0.0, 0]}, "[1.0, 0]": {"num_count": 2853, "sum_payoffs": 533.1267827747589, "action": [1.0, 0]}}, "1": {"[0.0, 0]": {"num_count": 231, "sum_payoffs": 33.41137499248239, "action": [0.0, 0]}, "[1.0, 0]": {"num_count": 2869, "sum_payoffs": 542.2797827727007, "action": [1.0, 0]}}}, "1": {"0": {"[1.0, 0]": {"num_count": 2895, "sum_payoffs": 594.8324998661628, "action": [1.0, 0]}, "[0.0, 0]": {"num_count": 205, "sum_payoffs": 32.8499999926088, "action": [0.0, 0]}}, "1": {"[0.0, 0]": {"num_count": 221, "sum_payoffs": 37.60874999153811, "action": [0.0, 0]}, "[1.0, 0]": {"num_count": 2879, "sum_payoffs": 593.1112498665498, "action": [1.0, 0]}}}}