{"2": {"0": {"[0.0, 0]": {"num_count": 249, "sum_payoffs": 27.976539468555185, "action": [0.0, 0]}, "[1.0, 0]": {"num_count": 351, "sum_payoffs": 51.95399999047483, "action": [1.0, 0]}}, "1": {"[0.0, 0]": {"num_count": 251, "sum_payoffs": 28.766289468410402, "action": [0.0, 0]}, "[1.0, 0]": {"num_count": 349, "sum_payoffs": 52.01474999046369, "action": [1.0, 0]}}}, "1": {"0": {"[0.0, 0]": {"num_count": 262, "sum_payoffs": 32.25749999408608, "action": [0.0, 0]}, "[1.0, 0]": {"num_count": 338, "sum_payoffs": 50.474999990746184, "action": [1.0, 0]}}, "1": {"[1.0, 0]": {"num_count": 337, "sum_payoffs": 50.40749999075856, "action": [1.0, 0]}, "[0.0, 0]": {"num_count": 263, "sum_payoffs": 32.59499999402421, "action": [0.0, 0]}}}}