{"2": {"0": {"[1.0, 0]": {"num_count": 4301, "sum_payoffs": 690.5654660470024, "action": [1.0, 0]}, "[0.0, 0]": {"num_count": 299, "sum_payoffs": 35.98814097127426, "action": [0.0, 0]}}, "1": {"[0.0, 0]": {"num_count": 321, "sum_payoffs": 40.90310525614597, "action": [0.0, 0]}, "[1.0, 0]": {"num_count": 4279, "sum_payoffs": 681.901358905631, "action": [1.0, 0]}}}, "1": {"0": {"[0.0, 0]": {"num_count": 332, "sum_payoffs": 47.986071420345034, "action": [0.0, 0]}, "[1.0, 0]": {"num_count": 4268, "sum_payoffs": 747.9064284431817, "action": [1.0, 0]}}, "1": {"[0.0, 0]": {"num_count": 298, "sum_payoffs": 45.816428563574156, "action": [0.0, 0]}, "[1.0, 0]": {"num_count": 4302, "sum_payoffs": 758.2339284414106, "action": [1.0, 0]}}}}