{"2": {"0": {"[0.0, 0]": {"num_count": 56, "sum_payoffs": 16.22024999567461, "action": [0.0, 0]}, "[1.0, 0]": {"num_count": 544, "sum_payoffs": 202.66199994595547, "action": [1.0, 0]}}, "1": {"[0.0, 0]": {"num_count": 68, "sum_payoffs": 17.86049999523721, "action": [0.0, 0]}, "[1.0, 0]": {"num_count": 532, "sum_payoffs": 200.29274994658738, "action": [1.0, 0]}}}, "1": {"0": {"[0.0, 0]": {"num_count": 110, "sum_payoffs": 36.44999999027994, "action": [0.0, 0]}, "[1.0, 0]": {"num_count": 490, "sum_payoffs": 200.87999994643144, "action": [1.0, 0]}}, "1": {"[0.0, 0]": {"num_count": 61, "sum_payoffs": 22.47749999400599, "action": [0.0, 0]}, "[1.0, 0]": {"num_count": 539, "sum_payoffs": 226.19249993968137, "action": [1.0, 0]}}}}