{"2": {"0": {"[1.0, 0]": {"num_count": 977, "sum_payoffs": 189.32737493373435, "action": [1.0, 0]}, "[0.0, 0]": {"num_count": 123, "sum_payoffs": 18.700874993454654, "action": [0.0, 0]}}, "1": {"[0.0, 0]": {"num_count": 134, "sum_payoffs": 19.79437499307192, "action": [0.0, 0]}, "[1.0, 0]": {"num_count": 966, "sum_payoffs": 182.03737493628606, "action": [1.0, 0]}}}, "1": {"0": {"[0.0, 0]": {"num_count": 100, "sum_payoffs": 17.864999993747247, "action": [0.0, 0]}, "[1.0, 0]": {"num_count": 1000, "sum_payoffs": 207.34874992743187, "action": [1.0, 0]}}, "1": {"[1.0, 0]": {"num_count": 996, "sum_payoffs": 205.8299999279633, "action": [1.0, 0]}, "[0.0, 0]": {"num_count": 104, "sum_payoffs": 17.358749993924445, "action": [0.0, 0]}}}}