{"2": {"0": {"[1.0, 0]": {"num_count": 4314, "sum_payoffs": 917.5462780381508, "action": [1.0, 0]}, "[0.0, 0]": {"num_count": 286, "sum_payoffs": 45.54899999219172, "action": [0.0, 0]}}, "1": {"[0.0, 0]": {"num_count": 297, "sum_payoffs": 48.22585713458998, "action": [0.0, 0]}, "[1.0, 0]": {"num_count": 4303, "sum_payoffs": 914.0362780387526, "action": [1.0, 0]}}}, "1": {"0": {"[0.0, 0]": {"num_count": 288, "sum_payoffs": 58.70571427565023, "action": [0.0, 0]}, "[1.0, 0]": {"num_count": 4312, "sum_payoffs": 1006.9071426844316, "action": [1.0, 0]}}, "1": {"[0.0, 0]": {"num_count": 259, "sum_payoffs": 51.762857133983324, "action": [0.0, 0]}, "[1.0, 0]": {"num_count": 4341, "sum_payoffs": 1014.3128569688741, "action": [1.0, 0]}}}}