{"2": {"0": {"[1.0, 0]": {"num_count": 1907, "sum_payoffs": 162.1683473359901, "action": [1.0, 0]}, "[0.0, 0]": {"num_count": 1193, "sum_payoffs": 72.4778999855041, "action": [0.0, 0]}}, "1": {"[0.0, 0]": {"num_count": 1189, "sum_payoffs": 72.17329735398604, "action": [0.0, 0]}, "[1.0, 0]": {"num_count": 1911, "sum_payoffs": 162.91034996742056, "action": [1.0, 0]}}}, "1": {"0": {"[1.0, 0]": {"num_count": 1830, "sum_payoffs": 163.60199996727684, "action": [1.0, 0]}, "[0.0, 0]": {"num_count": 1270, "sum_payoffs": 89.69849998206126, "action": [0.0, 0]}}, "1": {"[1.0, 0]": {"num_count": 1831, "sum_payoffs": 163.7234999672525, "action": [1.0, 0]}, "[0.0, 0]": {"num_count": 1269, "sum_payoffs": 89.57699998208557, "action": [0.0, 0]}}}}