{"2": {"0": {"[1.0, 0]": {"num_count": 1046, "sum_payoffs": 3.3299999988345004, "action": [1.0, 0]}, "[0.0, 0]": {"num_count": 1054, "sum_payoffs": 3.8036842091950267, "action": [0.0, 0]}}, "1": {"[0.0, 0]": {"num_count": 1054, "sum_payoffs": 3.8036842091950267, "action": [0.0, 0]}, "[1.0, 0]": {"num_count": 1046, "sum_payoffs": 3.3299999988345004, "action": [1.0, 0]}}}, "1": {"0": {"[0.0, 0]": {"num_count": 1065, "sum_payoffs": 1.79999999937, "action": [0.0, 0]}, "[1.0, 0]": {"num_count": 1035, "sum_payoffs": 0.0, "action": [1.0, 0]}}, "1": {"[1.0, 0]": {"num_count": 1050, "sum_payoffs": 0.899999999685, "action": [1.0, 0]}, "[0.0, 0]": {"num_count": 1050, "sum_payoffs": 0.899999999685, "action": [0.0, 0]}}}}