{"2": {"0": {"[0.0, 0]": {"num_count": 915, "sum_payoffs": 295.0627498967287, "action": [0.0, 0]}, "[1.0, 0]": {"num_count": 2685, "sum_payoffs": 1015.3147496446755, "action": [1.0, 0]}}, "1": {"[0.0, 0]": {"num_count": 945, "sum_payoffs": 307.82024989226375, "action": [0.0, 0]}, "[1.0, 0]": {"num_count": 2655, "sum_payoffs": 1005.8377496479909, "action": [1.0, 0]}}}, "1": {"0": {"[1.0, 0]": {"num_count": 2330, "sum_payoffs": 967.5449996613207, "action": [1.0, 0]}, "[0.0, 0]": {"num_count": 1270, "sum_payoffs": 489.44249982870264, "action": [0.0, 0]}}, "1": {"[1.0, 0]": {"num_count": 2320, "sum_payoffs": 963.8999996625969, "action": [1.0, 0]}, "[0.0, 0]": {"num_count": 1280, "sum_payoffs": 494.70749982685993, "action": [0.0, 0]}}}}