{"2": {"0": {"[1.0, 0]": {"num_count": 3805, "sum_payoffs": 603.6058893529503, "action": [1.0, 0]}, "[0.0, 0]": {"num_count": 295, "sum_payoffs": 40.45211051822539, "action": [0.0, 0]}}, "1": {"[1.0, 0]": {"num_count": 455, "sum_payoffs": 71.91648945930069, "action": [1.0, 0]}, "[0.0, 0]": {"num_count": 3645, "sum_payoffs": 493.40951042764476, "action": [0.0, 0]}}}, "1": {"0": {"[0.0, 0]": {"num_count": 246, "sum_payoffs": 39.93299999201325, "action": [0.0, 0]}, "[1.0, 0]": {"num_count": 3854, "sum_payoffs": 674.7569998650501, "action": [1.0, 0]}}, "1": {"[1.0, 0]": {"num_count": 3820, "sum_payoffs": 599.777999880033, "action": [1.0, 0]}, "[0.0, 0]": {"num_count": 280, "sum_payoffs": 16.091999996781517, "action": [0.0, 0]}}}}