{"2": {"0": {"[0.0, 0]": {"num_count": 771, "sum_payoffs": 245.12624985292098, "action": [0.0, 0]}, "[1.0, 0]": {"num_count": 2329, "sum_payoffs": 883.5479994698558, "action": [1.0, 0]}}, "1": {"[1.0, 0]": {"num_count": 2310, "sum_payoffs": 878.0804994731346, "action": [1.0, 0]}, "[0.0, 0]": {"num_count": 790, "sum_payoffs": 253.50974984789096, "action": [0.0, 0]}}}, "1": {"0": {"[0.0, 0]": {"num_count": 1080, "sum_payoffs": 414.11249975154004, "action": [0.0, 0]}, "[1.0, 0]": {"num_count": 2020, "sum_payoffs": 840.98249949544, "action": [1.0, 0]}}, "1": {"[1.0, 0]": {"num_count": 2018, "sum_payoffs": 840.577499495683, "action": [1.0, 0]}, "[0.0, 0]": {"num_count": 1082, "sum_payoffs": 415.32749975081117, "action": [0.0, 0]}}}}