{"2": {"0": {"[1.0, 0]": {"num_count": 62, "sum_payoffs": 15.582907889282813, "action": [1.0, 0]}, "[0.0, 0]": {"num_count": 38, "sum_payoffs": 8.584342102258638, "action": [0.0, 0]}}, "1": {"[1.0, 0]": {"num_count": 54, "sum_payoffs": 14.392657889699404, "action": [1.0, 0]}, "[0.0, 0]": {"num_count": 46, "sum_payoffs": 9.592342101905833, "action": [0.0, 0]}}}, "1": {"0": {"[0.0, 0]": {"num_count": 58, "sum_payoffs": 10.878749996192434, "action": [0.0, 0]}, "[1.0, 0]": {"num_count": 42, "sum_payoffs": 10.316249996389317, "action": [1.0, 0]}}, "1": {"[0.0, 0]": {"num_count": 50, "sum_payoffs": 9.76499999658225, "action": [0.0, 0]}, "[1.0, 0]": {"num_count": 50, "sum_payoffs": 12.442499995645129, "action": [1.0, 0]}}}}