{"2": {"0": {"[0.0, 0]": {"num_count": 654, "sum_payoffs": 40.528349991894046, "action": [0.0, 0]}, "[1.0, 0]": {"num_count": 946, "sum_payoffs": 82.56820261506518, "action": [1.0, 0]}}, "1": {"[1.0, 0]": {"num_count": 954, "sum_payoffs": 84.16390261474612, "action": [1.0, 0]}, "[0.0, 0]": {"num_count": 646, "sum_payoffs": 39.734549992052834, "action": [0.0, 0]}}}, "1": {"0": {"[1.0, 0]": {"num_count": 817, "sum_payoffs": 68.46749998630732, "action": [1.0, 0]}, "[0.0, 0]": {"num_count": 783, "sum_payoffs": 63.29249998734227, "action": [0.0, 0]}}, "1": {"[1.0, 0]": {"num_count": 817, "sum_payoffs": 68.46749998630732, "action": [1.0, 0]}, "[0.0, 0]": {"num_count": 783, "sum_payoffs": 63.29249998734227, "action": [0.0, 0]}}}}