{"2": {"0": {"[0.0, 0]": {"num_count": 221, "sum_payoffs": 35.195007512763574, "action": [0.0, 0]}, "[1.0, 0]": {"num_count": 3379, "sum_payoffs": 719.4665637864047, "action": [1.0, 0]}}, "1": {"[0.0, 0]": {"num_count": 237, "sum_payoffs": 37.76772179803686, "action": [0.0, 0]}, "[1.0, 0]": {"num_count": 3363, "sum_payoffs": 717.1021352153815, "action": [1.0, 0]}}}, "1": {"0": {"[0.0, 0]": {"num_count": 246, "sum_payoffs": 48.522857134538775, "action": [0.0, 0]}, "[1.0, 0]": {"num_count": 3354, "sum_payoffs": 784.7357141511384, "action": [1.0, 0]}}, "1": {"[0.0, 0]": {"num_count": 257, "sum_payoffs": 51.76285713398331, "action": [0.0, 0]}, "[1.0, 0]": {"num_count": 3343, "sum_payoffs": 783.5785712941938, "action": [1.0, 0]}}}}