{"2": {"0": {"[1.0, 0]": {"num_count": 1443, "sum_payoffs": 269.18378283417235, "action": [1.0, 0]}, "[0.0, 0]": {"num_count": 157, "sum_payoffs": 22.496092100201537, "action": [0.0, 0]}}, "1": {"[0.0, 0]": {"num_count": 133, "sum_payoffs": 20.588092100630845, "action": [0.0, 0]}, "[1.0, 0]": {"num_count": 1467, "sum_payoffs": 280.0220328317322, "action": [1.0, 0]}}}, "1": {"0": {"[1.0, 0]": {"num_count": 1459, "sum_payoffs": 301.00499993227214, "action": [1.0, 0]}, "[0.0, 0]": {"num_count": 141, "sum_payoffs": 25.458749994271784, "action": [0.0, 0]}}, "1": {"[1.0, 0]": {"num_count": 1450, "sum_payoffs": 298.4737499328415, "action": [1.0, 0]}, "[0.0, 0]": {"num_count": 150, "sum_payoffs": 25.762499994203424, "action": [0.0, 0]}}}}