{"2": {"0": {"[0.0, 0]": {"num_count": 438, "sum_payoffs": 34.61906249221072, "action": [0.0, 0]}, "[1.0, 0]": {"num_count": 662, "sum_payoffs": 74.48704932534626, "action": [1.0, 0]}}, "1": {"[1.0, 0]": {"num_count": 664, "sum_payoffs": 74.94267432524373, "action": [1.0, 0]}, "[0.0, 0]": {"num_count": 436, "sum_payoffs": 34.436812492251725, "action": [0.0, 0]}}}, "1": {"0": {"[0.0, 0]": {"num_count": 531, "sum_payoffs": 53.22374998802512, "action": [0.0, 0]}, "[1.0, 0]": {"num_count": 569, "sum_payoffs": 60.125624986472296, "action": [1.0, 0]}}, "1": {"[0.0, 0]": {"num_count": 531, "sum_payoffs": 53.22374998802512, "action": [0.0, 0]}, "[1.0, 0]": {"num_count": 569, "sum_payoffs": 60.1256249864723, "action": [1.0, 0]}}}}