{"2": {"0": {"[1.0, 0]": {"num_count": 4258, "sum_payoffs": 790.2309077169514, "action": [1.0, 0]}, "[0.0, 0]": {"num_count": 342, "sum_payoffs": 47.211749989377225, "action": [0.0, 0]}}, "1": {"[1.0, 0]": {"num_count": 4344, "sum_payoffs": 813.8322827116463, "action": [1.0, 0]}, "[0.0, 0]": {"num_count": 256, "sum_payoffs": 37.82587499148916, "action": [0.0, 0]}}}, "1": {"0": {"[0.0, 0]": {"num_count": 292, "sum_payoffs": 51.98624998830339, "action": [0.0, 0]}, "[1.0, 0]": {"num_count": 4308, "sum_payoffs": 879.648749802024, "action": [1.0, 0]}}, "1": {"[0.0, 0]": {"num_count": 300, "sum_payoffs": 54.82124998766556, "action": [0.0, 0]}, "[1.0, 0]": {"num_count": 4300, "sum_payoffs": 879.0412498021614, "action": [1.0, 0]}}}}